journeylib/__init__.py
journeylib/funciones.py
journeylib/tests.py
journeygenlib-0.0.1.dist-info/METADATA
journeygenlib-0.0.1.dist-info/WHEEL
journeygenlib-0.0.1.dist-info/top_level.txt
journeygenlib-0.0.1.dist-info/RECORD
