Metadata-Version: 2.1
Name: journeygenlib
Version: 0.0.1
Summary: Libreria para gestionar datos del historico del proyecto GPTravel
Home-page: https://ismigit.fi.upm.es/gptravel-2024/ai-squad/journeygenai
Author: Equipo JourneyGen UPM
Author-email: f.gonzalez.lopez@alumnos.upm.es
License: MIT
Platform: UNKNOWN
Requires-Dist: fastapi
Requires-Dist: requests
